{
  "awsRequestId": "88876ac4-83b4-458d-84f8-1ba3098db564",
  "apiRequestId": "TB8sRhqEIAMEViQ=",
  "x-correlation-trace-id": "Root=1-62970e4e-1553502123fcef6e57ead01c;Parent=1988f4d5727720e3;Sampled=0",
  "x-correlation-id": "88876ac4-83b4-458d-84f8-1ba3098db564",
  "level": 30,
  "time": 1654066767601,
  "pid": 9,
  "hostname": "169.254.88.193",
  "version": "2.0",
  "routeKey": "ANY /incoming-message",
  "rawPath": "/incoming-message",
  "rawQueryString": "",
  "headers": {
    "accept": "*/*",
    "accept-encoding": "deflate, gzip",
    "content-length": "593",
    "content-type": "application/json",
    "host": "uitm75njjc.execute-api.us-east-1.amazonaws.com",
    "user-agent": "facebookexternalua",
    "x-amzn-trace-id": "Root=1-62970e4e-51b392b477ba9d0234331cd3",
    "x-forwarded-for": "173.252.127.119",
    "x-forwarded-port": "443",
    "x-forwarded-proto": "https",
    "x-hub-signature": "sha1=d98ae054ae769a1b6d41d11ce6a210d916670f83"
  },
  "requestContext": {
    "accountId": "350346734421",
    "apiId": "uitm75njjc",
    "domainName": "uitm75njjc.execute-api.us-east-1.amazonaws.com",
    "domainPrefix": "uitm75njjc",
    "http": {
      "method": "POST",
      "path": "/incoming-message",
      "protocol": "HTTP/1.1",
      "sourceIp": "173.252.127.119",
      "userAgent": "facebookexternalua"
    },
    "requestId": "TB8sRhqEIAMEViQ=",
    "routeKey": "ANY /incoming-message",
    "stage": "$default",
    "time": "01/Jun/2022:06:59:26 +0000",
    "timeEpoch": 1654066766317
  },
  "body": "{\"object\":\"whatsapp_business_account\",\"entry\":[{\"id\":\"100482199363158\",\"changes\":[{\"value\":{\"messaging_product\":\"whatsapp\",\"metadata\":{\"display_phone_number\":\"972523362105\",\"phone_number_id\":\"104228662315144\"},\"contacts\":[{\"profile\":{\"name\":\"Shilo Magen\"},\"wa_id\":\"972544412112\"}],\"messages\":[{\"from\":\"972544412112\",\"id\":\"wamid.HBgMOTcyNTQ0NDEyMTEyFQIAEhgUM0VCMDUyNUU3RDI4MDM2NzdGOTMA\",\"timestamp\":\"1654065701\",\"type\":\"audio\",\"audio\":{\"mime_type\":\"audio\\/ogg; codecs=opus\",\"sha256\":\"cTCJNc2ri9DlrRFnVTofZRQycfmybnsDHeKsRepKjks=\",\"id\":\"3265168743761105\",\"voice\":true}}]},\"field\":\"messages\"}]}]}",
  "isBase64Encoded": false,
  "msg": "CloudApiIncomingMessage"
}
